Workbook

Sheet README
A1: MuddleAndMix — 12-month financial model
A2: Prepared 2026-10-12 for Richard Bailey. All forward-looking numbers are ASSUMPTIONS / ESTIMATES, not data.
A3: Yellow cells on 'Assumptions' and 'AI Unit Costs' are inputs. Everything else is formula-driven.
A4: Three scenario tabs (Model_Conservative / Model_Base / Model_Upside) use the same formulas with different input columns.
A5: Sourced facts (API prices, competitor prices) are on 'Benchmarks' with links. Assumptions with no source are labeled 'Assumption'.
A6: Richard's time is NOT costed. Taxes, LLC formation, and legal review are NOT included.
A7: The model asks one question: can this cover its own costs and show paying demand within 12 months? It is not a valuation.

Sheet Summary
A1: Scenario summary (formula links)
A3: Metric | B3: Conservative | C3: Base | D3: Upside
A4: Month-12 active users | B4: =Model_Conservative!N6 -> 26.900671 | C4: =Model_Base!N6 -> 329.18157 | D4: =Model_Upside!N6 -> 2580.0809
A5: Month-12 Home Pro paying users | B5: =Model_Conservative!N7 -> 0.40351006 | C5: =Model_Base!N7 -> 9.8754471 | D5: =Model_Upside!N7 -> 129.00405
A6: Month-12 Host/Pro accounts | B6: =Model_Conservative!N9 -> 2.7634587 | C6: =Model_Base!N9 -> 14.790024 | D6: =Model_Upside!N9 -> 30.7466
A7: Month-12 MRR (total revenue in M12) | B7: =Model_Conservative!M12 -> 53.345017 | C7: =Model_Base!M12 -> 315.57451 | D7: =Model_Upside!M12 -> 1177.604
A8: 12-month revenue | B8: =Model_Conservative!N12 -> 233.54663 | C8: =Model_Base!N12 -> 1680.2073 | D8: =Model_Upside!N12 -> 5494.2136
A9: 12-month costs | B9: =Model_Conservative!N17 -> 540.16961 | C9: =Model_Base!N17 -> 1417.5506 | D9: =Model_Upside!N17 -> 4515.5463
A10: 12-month net | B10: =Model_Conservative!N18 -> -306.62299 | C10: =Model_Base!N18 -> 262.65677 | D10: =Model_Upside!N18 -> 978.66739
A11: 12-month AI cost | B11: =Model_Conservative!N14 -> 141.48588 | C11: =Model_Base!N14 -> 579.81364 | D11: =Model_Upside!N14 -> 2342.8297
A14: Read: even the upside case is a side-income business in year 1, not a salary. The model's job is to show if paying demand appears cheaply.

Sheet Assumptions
A1: Inputs by scenario (yellow = editable)
A3: Key | B3: Assumption | C3: Conservative | D3: Base | E3: Upside | F3: Unit | G3: Basis / source
A4: visitors_m1 | B4: Month-1 unique visitors to site | C4: 150 | D4: 300 | E4: 600 | F4: visitors | G4: Assumption. Organic only: Reddit/forums posts, SEO pages, friends. No ad data yet.
A5: visitor_growth | B5: Monthly visitor growth | C5: 0.1 | D5: 0.2 | E5: 0.3 | F5: %/mo | G5: Assumption. Content/SEO compounding; heavily dependent on Richard's posting cadence.
A6: signup_rate | B6: Visitor → Google sign-up conversion | C6: 0.04 | D6: 0.08 | E6: 0.12 | F6: % | G6: Assumption. Free product + one-click Google sign-in; landing pages typically convert single digits.
A7: retention | B7: Month-over-month retention of active users | C7: 0.4 | D7: 0.55 | E7: 0.65 | F7: % | G7: Assumption. Hobby utilities are used episodically (parties, new bottles).
A8: paid_rate | B8: Share of active home users paying (Home Pro) | C8: 0.015 | D8: 0.03 | E8: 0.05 | F8: % | G8: Assumption. Freemium consumer apps commonly land low single digits.
A9: arppu | B9: Home Pro blended revenue per paying user | C9: 2.08 | D9: 2.5 | E9: 3 | F9: $/mo | G9: Assumption. $24.99/yr = $2.08/mo; $3.99/mo monthly. Mix of annual/monthly.
A10: host_launch | B10: Month Host/Pro tier launches | C10: 6 | D10: 4 | E10: 4 | F10: month # | G10: Plan. Only after home tier proves engagement.
A11: host_new | B11: New Host/Pro accounts per month after launch | C11: 0.5 | D11: 2 | E11: 4 | F11: accts/mo | G11: Assumption. Direct outreach to mobile bartenders / small cocktail venues.
A12: host_churn | B12: Host/Pro monthly churn | C12: 0.08 | D12: 0.05 | E12: 0.04 | F12: %/mo | G12: Assumption. Small-business SaaS churn is higher than enterprise.
A13: host_price | B13: Host/Pro price | C13: 19 | D13: 19 | E13: 19 | F13: $/mo | G13: Plan. Below Baraxis $29/mo and Backbar Essential $79/mo (see Benchmarks).
A14: aff_rev | B14: Affiliate revenue per active user | C14: 0 | D14: 0.03 | E14: 0.08 | F14: $/mo | G14: Speculative. ReserveBar affiliate reported ~4%, 30-day cookie (third-party listings).
A15: ai_user | B15: AI cost per active home user | C15: 0.6 | D15: 0.27 | E15: 0.2 | F15: $/mo | G15: Estimate: 'AI Unit Costs' tab computes ≈$0.19; base adds ~40% buffer for retries/long pages. Conservative = heavier use; Upside = move some calls to gpt-4o-mini.
... A21: pay_fee | B21: Effective payment fees (Stripe) | C21: 0.08 | D21: 0.06 | E21: 0.05 | F21: % of rev | G21: Stripe 2.9% + $0.30; $0.30 on a $3.99 charge ≈ 7.5% extra, on $24.99 ≈ 1.2%.

Sheet AI Unit Costs
A1: AI cost per action (estimate) — model names taken from server/routes.ts
A2: Prices: OpenAI gpt-4o $2.50/M input, $10/M output; gpt-4o-mini $0.15/M input, $0.60/M output (developers.openai.com). Token counts are ESTIMATES.
A4: Action (endpoint) | B4: Model | C4: Input tokens (est.) | D4: Output tokens (est.) | E4: $/M in | F4: $/M out | G4: Cost per action | H4: Uses / active user / mo (assumption) | I4: Cost / user / mo
A5: Bottle photo scan (/bottles/scan) | B5: gpt-4o | C5: 1300 | D5: 250 | E5: 2.5 | F5: 10 | G5: =C5/1000000*E5+D5/1000000*F5 -> 0.00575 | H5: 6 | I5: =G5*H5 -> 0.0345
A6: UPC lookup + normalize (/bottles/upc-lookup) | B6: gpt-4o-mini | C6: 600 | D6: 200 | E6: 0.15 | F6: 0.6 | G6: =C6/1000000*E6+D6/1000000*F6 -> 0.00021 | H6: 6 | I6: =G6*H6 -> 0.00126
A7: Recipe import from URL (/recipes/parse-url, page text capped 15k chars) | B7: gpt-4o | C7: 4500 | D7: 900 | E7: 2.5 | F7: 10 | G7: =C7/1000000*E7+D7/1000000*F7 -> 0.02025 | H7: 3 | I7: =G7*H7 -> 0.06075
A8: Recipe import from pasted text (/recipes/parse-text) | B8: gpt-4o | C8: 1500 | D8: 900 | E8: 2.5 | F8: 10 | G8: =C8/1000000*E8+D8/1000000*F8 -> 0.01275 | H8: 2 | I8: =G8*H8 -> 0.0255
A9: Recipe photo scan (/recipes/scan) | B9: gpt-4o | C9: 1500 | D9: 900 | E9: 2.5 | F9: 10 | G9: =C9/1000000*E9+D9/1000000*F9 -> 0.01275 | H9: 1 | I9: =G9*H9 -> 0.01275
A10: Discover 60 names (/recipes/discover) | B10: gpt-4o | C10: 400 | D10: 700 | E10: 2.5 | F10: 10 | G10: =C10/1000000*E10+D10/1000000*F10 -> 0.008 | H10: 1 | I10: =G10*H10 -> 0.008
A11: Import 10 named recipes (/recipes/import-names) | B11: gpt-4o | C11: 600 | D11: 5000 | E11: 2.5 | F11: 10 | G11: =C11/1000000*E11+D11/1000000*F11 -> 0.0515 | H11: 1 | I11: =G11*H11 -> 0.0515
A12: Estimated AI cost per active home user per month (base) | I12: =SUM(I5:I11) -> 0.19426
A14: Same usage if every gpt-4o call moved to gpt-4o-mini (≈16x cheaper per token): | I14: =I12*0.15/2.5 -> 0.0116556
A15: Guardrail suggestion: free tier capped at ~10 AI actions/month → worst-case free-user AI cost ≈ 10 × most expensive action: | I15: =10*MAX(G5:G11) -> 0.515

Sheet Model_Conservative
A1: Conservative scenario — 12 months (all values are estimates driven by 'Assumptions'!C)
A3: Line | B3: M1 | C3: M2 | D3: M3 | E3: M4 | F3: M5 | G3: M6 | H3: M7 | I3: M8 | J3: M9 | K3: M10 | L3: M11 | M3: M12 | N3: Total / M12
A4: Visitors | B4: =Assumptions!$C$4*(1+Assumptions!$C$5)^(1-1) -> 150 | C4: =Assumptions!$C$4*(1+Assumptions!$C$5)^(2-1) -> 165 | D4: =Assumptions!$C$4*(1+Assumptions!$C$5)^(3-1) -> 181.5 | E4: =Assumptions!$C$4*(1+Assumptions!$C$5)^(4-1) -> 199.65 | F4: =Assumptions!$C$4*(1+Assumptions!$C$5)^(5-1) -> 219.615 | G4: =Assumptions!$C$4*(1+Assumptions!$C$5)^(6-1) -> 241.5765 | H4: =Assumptions!$C$4*(1+Assumptions!$C$5)^(7-1) -> 265.73415 | I4: =Assumptions!$C$4*(1+Assumptions!$C$5)^(8-1) -> 292.30757 | J4: =Assumptions!$C$4*(1+Assumptions!$C$5)^(9-1) -> 321.53832 | K4: =Assumptions!$C$4*(1+Assumptions!$C$5)^(10-1) -> 353.69215 | L4: =Assumptions!$C$4*(1+Assumptions!$C$5)^(11-1) -> 389.06137 | M4: =Assumptions!$C$4*(1+Assumptions!$C$5)^(12-1) -> 427.96751 | N4: =SUM(B4:M4) -> 3207.6426
A5: New sign-ups | B5: =B4*Assumptions!$C$6 -> 6 | C5: =C4*Assumptions!$C$6 -> 6.6 | D5: =D4*Assumptions!$C$6 -> 7.26 | E5: =E4*Assumptions!$C$6 -> 7.986 | F5: =F4*Assumptions!$C$6 -> 8.7846 | G5: =G4*Assumptions!$C$6 -> 9.66306 | H5: =H4*Assumptions!$C$6 -> 10.629366 | I5: =I4*Assumptions!$C$6 -> 11.692303 | ... M5: =M4*Assumptions!$C$6 -> 17.1187 | N5: =SUM(B5:M5) -> 128.3057
A6: Active users | B6: =B5 -> 6 | C6: =B6*Assumptions!$C$7+C5 -> 9 | D6: =C6*Assumptions!$C$7+D5 -> 10.86 | E6: =D6*Assumptions!$C$7+E5 -> 12.33 | F6: =E6*Assumptions!$C$7+F5 -> 13.7166 | G6: =F6*Assumptions!$C$7+G5 -> 15.1497 | H6: =G6*Assumptions!$C$7+H5 -> 16.689246 | I6: =H6*Assumptions!$C$7+I5 -> 18.368001 | J6: =I6*Assumptions!$C$7+J5 -> 20.208733 | ... M6: =L6*Assumptions!$C$7+M5 -> 26.900671 | N6: =M6 -> 26.900671
A7: Home Pro paying users | B7: =B6*Assumptions!$C$8 -> 0.09 | C7: =C6*Assumptions!$C$8 -> 0.135 | D7: =D6*Assumptions!$C$8 -> 0.1629 | E7: =E6*Assumptions!$C$8 -> 0.18495 | F7: =F6*Assumptions!$C$8 -> 0.205749 | G7: =G6*Assumptions!$C$8 -> 0.2272455 | H7: =H6*Assumptions!$C$8 -> 0.25033869 | I7: =I6*Assumptions!$C$8 -> 0.27552002 | ... M7: =M6*Assumptions!$C$8 -> 0.40351006 | N7: =M7 -> 0.40351006
A8: Home Pro revenue | B8: =B7*Assumptions!$C$9 -> 0.1872 | C8: =C7*Assumptions!$C$9 -> 0.2808 | D8: =D7*Assumptions!$C$9 -> 0.338832 | E8: =E7*Assumptions!$C$9 -> 0.384696 | F8: =F7*Assumptions!$C$9 -> 0.42795792 | G8: =G7*Assumptions!$C$9 -> 0.47267064 | H8: =H7*Assumptions!$C$9 -> 0.52070448 | I8: =I7*Assumptions!$C$9 -> 0.57308163 | ... M8: =M7*Assumptions!$C$9 -> 0.83930093 | N8: =SUM(B8:M8) -> 6.1123626
A9: Host/Pro accounts | B9: =IF(1<Assumptions!$C$10,0,0*(1-Assumptions!$C$12)+Assumptions!$C$11) -> 0 | C9: =IF(2<Assumptions!$C$10,0,B9*(1-Assumptions!$C$12)+Assumptions!$C$11) -> 0 | D9: =IF(3<Assumptions!$C$10,0,C9*(1-Assumptions!$C$12)+Assumptions!$C$11) -> 0 | E9: =IF(4<Assumptions!$C$10,0,D9*(1-Assumptions!$C$12)+Assumptions!$C$11) -> 0 | F9: =IF(5<Assumptions!$C$10,0,E9*(1-Assumptions!$C$12)+Assumptions!$C$11) -> 0 | G9: =IF(6<Assumptions!$C$10,0,F9*(1-Assumptions!$C$12)+Assumptions!$C$11) -> 0.5 | H9: =IF(7<Assumptions!$C$10,0,G9*(1-Assumptions!$C$12)+Assumptions!$C$11) -> 0.96 | I9: =IF(8<Assumptions!$C$10,0,H9*(1-Assumptions!$C$12)+Assumptions!$C$11) -> 1.3832 | J9: =IF(9<Assumptions!$C$10,0,I9*(1-Assumptions!$C$12)+Assumptions!$C$11) -> 1.772544 | K9: =IF(10<Assumptions!$C$10,0,J9*(1-Assumptions!$C$12)+Assumptions!$C$11) -> 2.1307405 | L9: =IF(11<Assumptions!$C$10,0,K9*(1-Assumptions!$C$12)+Assumptions!$C$11) -> 2.4602812 | M9: =IF(12<Assumptions!$C$10,0,L9*(1-Assumptions!$C$12)+Assumptions!$C$11) -> 2.7634587 | N9: =M9 -> 2.7634587
A10: Host/Pro revenue | B10: =B9*Assumptions!$C$13 -> 0 | C10: =C9*Assumptions!$C$13 -> 0 | D10: =D9*Assumptions!$C$13 -> 0 | E10: =E9*Assumptions!$C$13 -> 0 | F10: =F9*Assumptions!$C$13 -> 0 | G10: =G9*Assumptions!$C$13 -> 9.5 | H10: =H9*Assumptions!$C$13 -> 18.24 | I10: =I9*Assumptions!$C$13 -> 26.2808 | ... M10: =M9*Assumptions!$C$13 -> 52.505716 | N10: =SUM(B10:M10) -> 227.43426
A11: Affiliate revenue | B11: =B6*Assumptions!$C$14 -> 0 | C11: =C6*Assumptions!$C$14 -> 0 | D11: =D6*Assumptions!$C$14 -> 0 | E11: =E6*Assumptions!$C$14 -> 0 | F11: =F6*Assumptions!$C$14 -> 0 | G11: =G6*Assumptions!$C$14 -> 0 | H11: =H6*Assumptions!$C$14 -> 0 | I11: =I6*Assumptions!$C$14 -> 0 | ... M11: =M6*Assumptions!$C$14 -> 0 | N11: =SUM(B11:M11) -> 0
A12: TOTAL REVENUE | B12: =B8+B10+B11 -> 0.1872 | C12: =C8+C10+C11 -> 0.2808 | D12: =D8+D10+D11 -> 0.338832 | E12: =E8+E10+E11 -> 0.384696 | F12: =F8+F10+F11 -> 0.42795792 | G12: =G8+G10+G11 -> 9.9726706 | H12: =H8+H10+H11 -> 18.760704 | I12: =I8+I10+I11 -> 26.853882 | ... M12: =M8+M10+M11 -> 53.345017 | N12: =SUM(B12:M12) -> 233.54663
A13: Payment fees | B13: =(B8+B10)*Assumptions!$C$21 -> 0.014976 | C13: =(C8+C10)*Assumptions!$C$21 -> 0.022464 | D13: =(D8+D10)*Assumptions!$C$21 -> 0.02710656 | E13: =(E8+E10)*Assumptions!$C$21 -> 0.03077568 | F13: =(F8+F10)*Assumptions!$C$21 -> 0.034236634 | G13: =(G8+G10)*Assumptions!$C$21 -> 0.79781365 | H13: =(H8+H10)*Assumptions!$C$21 -> 1.5008564 | I13: =(I8+I10)*Assumptions!$C$21 -> 2.1483105 | ... M13: =(M8+M10)*Assumptions!$C$21 -> 4.2676014 | N13: =SUM(B13:M13) -> 18.68373
A14: AI cost | B14: =B6*Assumptions!$C$15+B9*Assumptions!$C$16 -> 3.6 | C14: =C6*Assumptions!$C$15+C9*Assumptions!$C$16 -> 5.4 | D14: =D6*Assumptions!$C$15+D9*Assumptions!$C$16 -> 6.516 | E14: =E6*Assumptions!$C$15+E9*Assumptions!$C$16 -> 7.398 | F14: =F6*Assumptions!$C$15+F9*Assumptions!$C$16 -> 8.22996 | G14: =G6*Assumptions!$C$15+G9*Assumptions!$C$16 -> 10.08982 | H14: =H6*Assumptions!$C$15+H9*Assumptions!$C$16 -> 11.933548 | I14: =I6*Assumptions!$C$15+I9*Assumptions!$C$16 -> 13.787201 | ... M14: =M6*Assumptions!$C$15+M9*Assumptions!$C$16 -> 21.66732 | N14: =SUM(B14:M14) -> 141.48588
A15: Hosting + domain + data | B15: =Assumptions!$C$17+Assumptions!$C$18/12+Assumptions!$C$19 -> 31.666667 | C15: =Assumptions!$C$17+Assumptions!$C$18/12+Assumptions!$C$19 -> 31.666667 | D15: =Assumptions!$C$17+Assumptions!$C$18/12+Assumptions!$C$19 -> 31.666667 | E15: =Assumptions!$C$17+Assumptions!$C$18/12+Assumptions!$C$19 -> 31.666667 | F15: =Assumptions!$C$17+Assumptions!$C$18/12+Assumptions!$C$19 -> 31.666667 | G15: =Assumptions!$C$17+Assumptions!$C$18/12+Assumptions!$C$19 -> 31.666667 | H15: =Assumptions!$C$17+Assumptions!$C$18/12+Assumptions!$C$19 -> 31.666667 | I15: =Assumptions!$C$17+Assumptions!$C$18/12+Assumptions!$C$19 -> 31.666667 | ... M15: =Assumptions!$C$17+Assumptions!$C$18/12+Assumptions!$C$19 -> 31.666667 | N15: =SUM(B15:M15) -> 380
A16: Marketing | B16: =Assumptions!$C$20 -> 0 | C16: =Assumptions!$C$20 -> 0 | D16: =Assumptions!$C$20 -> 0 | E16: =Assumptions!$C$20 -> 0 | F16: =Assumptions!$C$20 -> 0 | G16: =Assumptions!$C$20 -> 0 | H16: =Assumptions!$C$20 -> 0 | I16: =Assumptions!$C$20 -> 0 | ... M16: =Assumptions!$C$20 -> 0 | N16: =SUM(B16:M16) -> 0
A17: TOTAL COSTS | B17: =SUM(B13:B16) -> 35.281643 | C17: =SUM(C13:C16) -> 37.089131 | D17: =SUM(D13:D16) -> 38.209773 | E17: =SUM(E13:E16) -> 39.095442 | F17: =SUM(F13:F16) -> 39.930863 | G17: =SUM(G13:G16) -> 42.5543 | H17: =SUM(H13:H16) -> 45.101071 | I17: =SUM(I13:I16) -> 47.602178 | ... M17: =SUM(M13:M16) -> 57.601588 | N17: =SUM(B17:M17) -> 540.16961
A18: NET (monthly) | B18: =B12-B17 -> -35.094443 | C18: =C12-C17 -> -36.808331 | D18: =D12-D17 -> -37.870941 | E18: =E12-E17 -> -38.710746 | F18: =F12-F17 -> -39.502905 | G18: =G12-G17 -> -32.58163 | H18: =H12-H17 -> -26.340366 | I18: =I12-I17 -> -20.748296 | ... M18: =M12-M17 -> -4.256571 | N18: =SUM(B18:M18) -> -306.62299
A19: Cumulative net | B19: =B18 -> -35.094443 | C19: =B19+C18 -> -71.902773 | D19: =C19+D18 -> -109.77371 | E19: =D19+E18 -> -148.48446 | F19: =E19+F18 -> -187.98737 | G19: =F19+G18 -> -220.569 | H19: =G19+H18 -> -246.90936 | I19: =H19+I18 -> -267.65766 | J19: =I19+J18 -> -283.43051 | ... M19: =L19+M18 -> -306.62299 | N19: =M19 -> -306.62299
A20: Blended paid CAC (marketing ÷ new sign-ups) | B20: =IFERROR(B16/B5,0) -> 0 | C20: =IFERROR(C16/C5,0) -> 0 | D20: =IFERROR(D16/D5,0) -> 0 | E20: =IFERROR(E16/E5,0) -> 0 | F20: =IFERROR(F16/F5,0) -> 0 | G20: =IFERROR(G16/G5,0) -> 0 | H20: =IFERROR(H16/H5,0) -> 0 | I20: =IFERROR(I16/I5,0) -> 0 | ... M20: =IFERROR(M16/M5,0) -> 0 | N20: =M20 -> 0
A22: Total column = 12-month sum for flows; month-12 value for stocks (users, accounts, cumulative net).

Sheet Model_Base
A1: Base scenario — 12 months (all values are estimates driven by 'Assumptions'!D)
A3: Line | B3: M1 | C3: M2 | D3: M3 | E3: M4 | F3: M5 | G3: M6 | H3: M7 | I3: M8 | J3: M9 | K3: M10 | L3: M11 | M3: M12 | N3: Total / M12
A4: Visitors | B4: =Assumptions!$D$4*(1+Assumptions!$D$5)^(1-1) -> 300 | C4: =Assumptions!$D$4*(1+Assumptions!$D$5)^(2-1) -> 360 | D4: =Assumptions!$D$4*(1+Assumptions!$D$5)^(3-1) -> 432 | E4: =Assumptions!$D$4*(1+Assumptions!$D$5)^(4-1) -> 518.4 | F4: =Assumptions!$D$4*(1+Assumptions!$D$5)^(5-1) -> 622.08 | G4: =Assumptions!$D$4*(1+Assumptions!$D$5)^(6-1) -> 746.496 | H4: =Assumptions!$D$4*(1+Assumptions!$D$5)^(7-1) -> 895.7952 | I4: =Assumptions!$D$4*(1+Assumptions!$D$5)^(8-1) -> 1074.9542 | J4: =Assumptions!$D$4*(1+Assumptions!$D$5)^(9-1) -> 1289.9451 | K4: =Assumptions!$D$4*(1+Assumptions!$D$5)^(10-1) -> 1547.9341 | L4: =Assumptions!$D$4*(1+Assumptions!$D$5)^(11-1) -> 1857.5209 | M4: =Assumptions!$D$4*(1+Assumptions!$D$5)^(12-1) -> 2229.0251 | N4: =SUM(B4:M4) -> 11874.151
A5: New sign-ups | B5: =B4*Assumptions!$D$6 -> 24 | C5: =C4*Assumptions!$D$6 -> 28.8 | D5: =D4*Assumptions!$D$6 -> 34.56 | E5: =E4*Assumptions!$D$6 -> 41.472 | F5: =F4*Assumptions!$D$6 -> 49.7664 | G5: =G4*Assumptions!$D$6 -> 59.71968 | H5: =H4*Assumptions!$D$6 -> 71.663616 | I5: =I4*Assumptions!$D$6 -> 85.996339 | ... M5: =M4*Assumptions!$D$6 -> 178.32201 | N5: =SUM(B5:M5) -> 949.93205
A6: Active users | B6: =B5 -> 24 | C6: =B6*Assumptions!$D$7+C5 -> 42 | D6: =C6*Assumptions!$D$7+D5 -> 57.66 | E6: =D6*Assumptions!$D$7+E5 -> 73.185 | F6: =E6*Assumptions!$D$7+F5 -> 90.01815 | G6: =F6*Assumptions!$D$7+G5 -> 109.22966 | H6: =G6*Assumptions!$D$7+H5 -> 131.73993 | I6: =H6*Assumptions!$D$7+I5 -> 158.4533 | J6: =I6*Assumptions!$D$7+J5 -> 190.34492 | ... M6: =L6*Assumptions!$D$7+M5 -> 329.18157 | N6: =M6 -> 329.18157
A7: Home Pro paying users | B7: =B6*Assumptions!$D$8 -> 0.72 | C7: =C6*Assumptions!$D$8 -> 1.26 | D7: =D6*Assumptions!$D$8 -> 1.7298 | E7: =E6*Assumptions!$D$8 -> 2.19555 | F7: =F6*Assumptions!$D$8 -> 2.7005445 | G7: =G6*Assumptions!$D$8 -> 3.2768899 | H7: =H6*Assumptions!$D$8 -> 3.9521979 | I7: =I6*Assumptions!$D$8 -> 4.753599 | ... M7: =M6*Assumptions!$D$8 -> 9.8754471 | N7: =M7 -> 9.8754471
A8: Home Pro revenue | B8: =B7*Assumptions!$D$9 -> 1.8 | C8: =C7*Assumptions!$D$9 -> 3.15 | D8: =D7*Assumptions!$D$9 -> 4.3245 | E8: =E7*Assumptions!$D$9 -> 5.488875 | F8: =F7*Assumptions!$D$9 -> 6.7513613 | G8: =G7*Assumptions!$D$9 -> 8.1922247 | H8: =H7*Assumptions!$D$9 -> 9.8804948 | I8: =I7*Assumptions!$D$9 -> 11.883998 | ... M8: =M7*Assumptions!$D$9 -> 24.688618 | N8: =SUM(B8:M8) -> 128.14703
A9: Host/Pro accounts | B9: =IF(1<Assumptions!$D$10,0,0*(1-Assumptions!$D$12)+Assumptions!$D$11) -> 0 | C9: =IF(2<Assumptions!$D$10,0,B9*(1-Assumptions!$D$12)+Assumptions!$D$11) -> 0 | D9: =IF(3<Assumptions!$D$10,0,C9*(1-Assumptions!$D$12)+Assumptions!$D$11) -> 0 | E9: =IF(4<Assumptions!$D$10,0,D9*(1-Assumptions!$D$12)+Assumptions!$D$11) -> 2 | F9: =IF(5<Assumptions!$D$10,0,E9*(1-Assumptions!$D$12)+Assumptions!$D$11) -> 3.9 | G9: =IF(6<Assumptions!$D$10,0,F9*(1-Assumptions!$D$12)+Assumptions!$D$11) -> 5.705 | H9: =IF(7<Assumptions!$D$10,0,G9*(1-Assumptions!$D$12)+Assumptions!$D$11) -> 7.41975 | I9: =IF(8<Assumptions!$D$10,0,H9*(1-Assumptions!$D$12)+Assumptions!$D$11) -> 9.0487625 | J9: =IF(9<Assumptions!$D$10,0,I9*(1-Assumptions!$D$12)+Assumptions!$D$11) -> 10.596324 | K9: =IF(10<Assumptions!$D$10,0,J9*(1-Assumptions!$D$12)+Assumptions!$D$11) -> 12.066508 | L9: =IF(11<Assumptions!$D$10,0,K9*(1-Assumptions!$D$12)+Assumptions!$D$11) -> 13.463183 | M9: =IF(12<Assumptions!$D$10,0,L9*(1-Assumptions!$D$12)+Assumptions!$D$11) -> 14.790024 | N9: =M9 -> 14.790024
A10: Host/Pro revenue | B10: =B9*Assumptions!$D$13 -> 0 | C10: =C9*Assumptions!$D$13 -> 0 | D10: =D9*Assumptions!$D$13 -> 0 | E10: =E9*Assumptions!$D$13 -> 38 | F10: =F9*Assumptions!$D$13 -> 74.1 | G10: =G9*Assumptions!$D$13 -> 108.395 | H10: =H9*Assumptions!$D$13 -> 140.97525 | I10: =I9*Assumptions!$D$13 -> 171.92649 | ... M10: =M9*Assumptions!$D$13 -> 281.01045 | N10: =SUM(B10:M10) -> 1500.8015
A11: Affiliate revenue | B11: =B6*Assumptions!$D$14 -> 0.72 | C11: =C6*Assumptions!$D$14 -> 1.26 | D11: =D6*Assumptions!$D$14 -> 1.7298 | E11: =E6*Assumptions!$D$14 -> 2.19555 | F11: =F6*Assumptions!$D$14 -> 2.7005445 | G11: =G6*Assumptions!$D$14 -> 3.2768899 | H11: =H6*Assumptions!$D$14 -> 3.9521979 | I11: =I6*Assumptions!$D$14 -> 4.753599 | ... M11: =M6*Assumptions!$D$14 -> 9.8754471 | N11: =SUM(B11:M11) -> 51.258813
A12: TOTAL REVENUE | B12: =B8+B10+B11 -> 2.52 | C12: =C8+C10+C11 -> 4.41 | D12: =D8+D10+D11 -> 6.0543 | E12: =E8+E10+E11 -> 45.684425 | F12: =F8+F10+F11 -> 83.551906 | G12: =G8+G10+G11 -> 119.86411 | H12: =H8+H10+H11 -> 154.80794 | I12: =I8+I10+I11 -> 188.56408 | ... M12: =M8+M10+M11 -> 315.57451 | N12: =SUM(B12:M12) -> 1680.2073
A13: Payment fees | B13: =(B8+B10)*Assumptions!$D$21 -> 0.108 | C13: =(C8+C10)*Assumptions!$D$21 -> 0.189 | D13: =(D8+D10)*Assumptions!$D$21 -> 0.25947 | E13: =(E8+E10)*Assumptions!$D$21 -> 2.6093325 | F13: =(F8+F10)*Assumptions!$D$21 -> 4.8510817 | G13: =(G8+G10)*Assumptions!$D$21 -> 6.9952335 | H13: =(H8+H10)*Assumptions!$D$21 -> 9.0513447 | I13: =(I8+I10)*Assumptions!$D$21 -> 11.028629 | ... M13: =(M8+M10)*Assumptions!$D$21 -> 18.341944 | N13: =SUM(B13:M13) -> 97.73691
A14: AI cost | B14: =B6*Assumptions!$D$15+B9*Assumptions!$D$16 -> 6.48 | C14: =C6*Assumptions!$D$15+C9*Assumptions!$D$16 -> 11.34 | D14: =D6*Assumptions!$D$15+D9*Assumptions!$D$16 -> 15.5682 | E14: =E6*Assumptions!$D$15+E9*Assumptions!$D$16 -> 22.75995 | F14: =F6*Assumptions!$D$15+F9*Assumptions!$D$16 -> 30.154901 | G14: =G6*Assumptions!$D$15+G9*Assumptions!$D$16 -> 38.049509 | H14: =H6*Assumptions!$D$15+H9*Assumptions!$D$16 -> 46.699406 | I14: =I6*Assumptions!$D$15+I9*Assumptions!$D$16 -> 56.355535 | ... M14: =M6*Assumptions!$D$15+M9*Assumptions!$D$16 -> 111.06406 | N14: =SUM(B14:M14) -> 579.81364
A15: Hosting + domain + data | B15: =Assumptions!$D$17+Assumptions!$D$18/12+Assumptions!$D$19 -> 11.666667 | C15: =Assumptions!$D$17+Assumptions!$D$18/12+Assumptions!$D$19 -> 11.666667 | D15: =Assumptions!$D$17+Assumptions!$D$18/12+Assumptions!$D$19 -> 11.666667 | E15: =Assumptions!$D$17+Assumptions!$D$18/12+Assumptions!$D$19 -> 11.666667 | F15: =Assumptions!$D$17+Assumptions!$D$18/12+Assumptions!$D$19 -> 11.666667 | G15: =Assumptions!$D$17+Assumptions!$D$18/12+Assumptions!$D$19 -> 11.666667 | H15: =Assumptions!$D$17+Assumptions!$D$18/12+Assumptions!$D$19 -> 11.666667 | I15: =Assumptions!$D$17+Assumptions!$D$18/12+Assumptions!$D$19 -> 11.666667 | ... M15: =Assumptions!$D$17+Assumptions!$D$18/12+Assumptions!$D$19 -> 11.666667 | N15: =SUM(B15:M15) -> 140
A16: Marketing | B16: =Assumptions!$D$20 -> 50 | C16: =Assumptions!$D$20 -> 50 | D16: =Assumptions!$D$20 -> 50 | E16: =Assumptions!$D$20 -> 50 | F16: =Assumptions!$D$20 -> 50 | G16: =Assumptions!$D$20 -> 50 | H16: =Assumptions!$D$20 -> 50 | I16: =Assumptions!$D$20 -> 50 | ... M16: =Assumptions!$D$20 -> 50 | N16: =SUM(B16:M16) -> 600
A17: TOTAL COSTS | B17: =SUM(B13:B16) -> 68.254667 | C17: =SUM(C13:C16) -> 73.195667 | D17: =SUM(D13:D16) -> 77.494337 | E17: =SUM(E13:E16) -> 87.035949 | F17: =SUM(F13:F16) -> 96.672649 | G17: =SUM(G13:G16) -> 106.71141 | H17: =SUM(H13:H16) -> 117.41742 | I17: =SUM(I13:I16) -> 129.05083 | ... M17: =SUM(M13:M16) -> 191.07267 | N17: =SUM(B17:M17) -> 1417.5506
A18: NET (monthly) | B18: =B12-B17 -> -65.734667 | C18: =C12-C17 -> -68.785667 | D18: =D12-D17 -> -71.440037 | E18: =E12-E17 -> -41.351524 | F18: =F12-F17 -> -13.120743 | G18: =G12-G17 -> 13.152706 | H18: =H12-H17 -> 37.390525 | I18: =I12-I17 -> 59.513253 | ... M18: =M12-M17 -> 124.50184 | N18: =SUM(B18:M18) -> 262.65677
A19: Cumulative net | B19: =B18 -> -65.734667 | C19: =B19+C18 -> -134.52033 | D19: =C19+D18 -> -205.96037 | E19: =D19+E18 -> -247.31189 | F19: =E19+F18 -> -260.43264 | G19: =F19+G18 -> -247.27993 | H19: =G19+H18 -> -209.88941 | I19: =H19+I18 -> -150.37615 | J19: =I19+J18 -> -70.950418 | ... M19: =L19+M18 -> 262.65677 | N19: =M19 -> 262.65677
A20: Blended paid CAC (marketing ÷ new sign-ups) | B20: =IFERROR(B16/B5,0) -> 2.0833333 | C20: =IFERROR(C16/C5,0) -> 1.7361111 | D20: =IFERROR(D16/D5,0) -> 1.4467593 | E20: =IFERROR(E16/E5,0) -> 1.2056327 | F20: =IFERROR(F16/F5,0) -> 1.0046939 | G20: =IFERROR(G16/G5,0) -> 0.83724494 | H20: =IFERROR(H16/H5,0) -> 0.69770412 | I20: =IFERROR(I16/I5,0) -> 0.5814201 | ... M20: =IFERROR(M16/M5,0) -> 0.28039164 | N20: =M20 -> 0.28039164
A22: Total column = 12-month sum for flows; month-12 value for stocks (users, accounts, cumulative net).

Sheet Model_Upside
A1: Upside scenario — 12 months (all values are estimates driven by 'Assumptions'!E)
A3: Line | B3: M1 | C3: M2 | D3: M3 | E3: M4 | F3: M5 | G3: M6 | H3: M7 | I3: M8 | J3: M9 | K3: M10 | L3: M11 | M3: M12 | N3: Total / M12
A4: Visitors | B4: =Assumptions!$E$4*(1+Assumptions!$E$5)^(1-1) -> 600 | C4: =Assumptions!$E$4*(1+Assumptions!$E$5)^(2-1) -> 780 | D4: =Assumptions!$E$4*(1+Assumptions!$E$5)^(3-1) -> 1014 | E4: =Assumptions!$E$4*(1+Assumptions!$E$5)^(4-1) -> 1318.2 | F4: =Assumptions!$E$4*(1+Assumptions!$E$5)^(5-1) -> 1713.66 | G4: =Assumptions!$E$4*(1+Assumptions!$E$5)^(6-1) -> 2227.758 | H4: =Assumptions!$E$4*(1+Assumptions!$E$5)^(7-1) -> 2896.0854 | I4: =Assumptions!$E$4*(1+Assumptions!$E$5)^(8-1) -> 3764.911 | J4: =Assumptions!$E$4*(1+Assumptions!$E$5)^(9-1) -> 4894.3843 | K4: =Assumptions!$E$4*(1+Assumptions!$E$5)^(10-1) -> 6362.6996 | L4: =Assumptions!$E$4*(1+Assumptions!$E$5)^(11-1) -> 8271.5095 | M4: =Assumptions!$E$4*(1+Assumptions!$E$5)^(12-1) -> 10752.962 | N4: =SUM(B4:M4) -> 44596.17
A5: New sign-ups | B5: =B4*Assumptions!$E$6 -> 72 | C5: =C4*Assumptions!$E$6 -> 93.6 | D5: =D4*Assumptions!$E$6 -> 121.68 | E5: =E4*Assumptions!$E$6 -> 158.184 | F5: =F4*Assumptions!$E$6 -> 205.6392 | G5: =G4*Assumptions!$E$6 -> 267.33096 | H5: =H4*Assumptions!$E$6 -> 347.53025 | I5: =I4*Assumptions!$E$6 -> 451.78932 | ... M5: =M4*Assumptions!$E$6 -> 1290.3555 | N5: =SUM(B5:M5) -> 5351.5404
A6: Active users | B6: =B5 -> 72 | C6: =B6*Assumptions!$E$7+C5 -> 140.4 | D6: =C6*Assumptions!$E$7+D5 -> 212.94 | E6: =D6*Assumptions!$E$7+E5 -> 296.595 | F6: =E6*Assumptions!$E$7+F5 -> 398.42595 | G6: =F6*Assumptions!$E$7+G5 -> 526.30783 | H6: =G6*Assumptions!$E$7+H5 -> 689.63034 | I6: =H6*Assumptions!$E$7+I5 -> 900.04904 | J6: =I6*Assumptions!$E$7+J5 -> 1172.358 | ... M6: =L6*Assumptions!$E$7+M5 -> 2580.0809 | N6: =M6 -> 2580.0809
A7: Home Pro paying users | B7: =B6*Assumptions!$E$8 -> 3.6 | C7: =C6*Assumptions!$E$8 -> 7.02 | D7: =D6*Assumptions!$E$8 -> 10.647 | E7: =E6*Assumptions!$E$8 -> 14.82975 | F7: =F6*Assumptions!$E$8 -> 19.921298 | G7: =G6*Assumptions!$E$8 -> 26.315391 | H7: =H6*Assumptions!$E$8 -> 34.481517 | I7: =I6*Assumptions!$E$8 -> 45.002452 | ... M7: =M6*Assumptions!$E$8 -> 129.00405 | N7: =M7 -> 129.00405
A8: Home Pro revenue | B8: =B7*Assumptions!$E$9 -> 10.8 | C8: =C7*Assumptions!$E$9 -> 21.06 | D8: =D7*Assumptions!$E$9 -> 31.941 | E8: =E7*Assumptions!$E$9 -> 44.48925 | F8: =F7*Assumptions!$E$9 -> 59.763892 | G8: =G7*Assumptions!$E$9 -> 78.946174 | H8: =H7*Assumptions!$E$9 -> 103.44455 | I8: =I7*Assumptions!$E$9 -> 135.00736 | ... M8: =M7*Assumptions!$E$9 -> 387.01214 | N8: =SUM(B8:M8) -> 1574.7805
A9: Host/Pro accounts | B9: =IF(1<Assumptions!$E$10,0,0*(1-Assumptions!$E$12)+Assumptions!$E$11) -> 0 | C9: =IF(2<Assumptions!$E$10,0,B9*(1-Assumptions!$E$12)+Assumptions!$E$11) -> 0 | D9: =IF(3<Assumptions!$E$10,0,C9*(1-Assumptions!$E$12)+Assumptions!$E$11) -> 0 | E9: =IF(4<Assumptions!$E$10,0,D9*(1-Assumptions!$E$12)+Assumptions!$E$11) -> 4 | F9: =IF(5<Assumptions!$E$10,0,E9*(1-Assumptions!$E$12)+Assumptions!$E$11) -> 7.84 | G9: =IF(6<Assumptions!$E$10,0,F9*(1-Assumptions!$E$12)+Assumptions!$E$11) -> 11.5264 | H9: =IF(7<Assumptions!$E$10,0,G9*(1-Assumptions!$E$12)+Assumptions!$E$11) -> 15.065344 | I9: =IF(8<Assumptions!$E$10,0,H9*(1-Assumptions!$E$12)+Assumptions!$E$11) -> 18.46273 | J9: =IF(9<Assumptions!$E$10,0,I9*(1-Assumptions!$E$12)+Assumptions!$E$11) -> 21.724221 | K9: =IF(10<Assumptions!$E$10,0,J9*(1-Assumptions!$E$12)+Assumptions!$E$11) -> 24.855252 | L9: =IF(11<Assumptions!$E$10,0,K9*(1-Assumptions!$E$12)+Assumptions!$E$11) -> 27.861042 | M9: =IF(12<Assumptions!$E$10,0,L9*(1-Assumptions!$E$12)+Assumptions!$E$11) -> 30.7466 | N9: =M9 -> 30.7466
A10: Host/Pro revenue | B10: =B9*Assumptions!$E$13 -> 0 | C10: =C9*Assumptions!$E$13 -> 0 | D10: =D9*Assumptions!$E$13 -> 0 | E10: =E9*Assumptions!$E$13 -> 76 | F10: =F9*Assumptions!$E$13 -> 148.96 | G10: =G9*Assumptions!$E$13 -> 219.0016 | H10: =H9*Assumptions!$E$13 -> 286.24154 | I10: =I9*Assumptions!$E$13 -> 350.79187 | ... M10: =M9*Assumptions!$E$13 -> 584.18541 | N10: =SUM(B10:M10) -> 3079.5502
A11: Affiliate revenue | B11: =B6*Assumptions!$E$14 -> 5.76 | C11: =C6*Assumptions!$E$14 -> 11.232 | D11: =D6*Assumptions!$E$14 -> 17.0352 | E11: =E6*Assumptions!$E$14 -> 23.7276 | F11: =F6*Assumptions!$E$14 -> 31.874076 | G11: =G6*Assumptions!$E$14 -> 42.104626 | H11: =H6*Assumptions!$E$14 -> 55.170427 | I11: =I6*Assumptions!$E$14 -> 72.003923 | ... M11: =M6*Assumptions!$E$14 -> 206.40647 | N11: =SUM(B11:M11) -> 839.88293
A12: TOTAL REVENUE | B12: =B8+B10+B11 -> 16.56 | C12: =C8+C10+C11 -> 32.292 | D12: =D8+D10+D11 -> 48.9762 | E12: =E8+E10+E11 -> 144.21685 | F12: =F8+F10+F11 -> 240.59797 | G12: =G8+G10+G11 -> 340.0524 | H12: =H8+H10+H11 -> 444.85651 | I12: =I8+I10+I11 -> 557.80315 | ... M12: =M8+M10+M11 -> 1177.604 | N12: =SUM(B12:M12) -> 5494.2136
A13: Payment fees | B13: =(B8+B10)*Assumptions!$E$21 -> 0.54 | C13: =(C8+C10)*Assumptions!$E$21 -> 1.053 | D13: =(D8+D10)*Assumptions!$E$21 -> 1.59705 | E13: =(E8+E10)*Assumptions!$E$21 -> 6.0244625 | F13: =(F8+F10)*Assumptions!$E$21 -> 10.436195 | G13: =(G8+G10)*Assumptions!$E$21 -> 14.897389 | H13: =(H8+H10)*Assumptions!$E$21 -> 19.484304 | I13: =(I8+I10)*Assumptions!$E$21 -> 24.289962 | ... M13: =(M8+M10)*Assumptions!$E$21 -> 48.559877 | N13: =SUM(B13:M13) -> 232.71654
A14: AI cost | B14: =B6*Assumptions!$E$15+B9*Assumptions!$E$16 -> 14.4 | C14: =C6*Assumptions!$E$15+C9*Assumptions!$E$16 -> 28.08 | D14: =D6*Assumptions!$E$15+D9*Assumptions!$E$16 -> 42.588 | E14: =E6*Assumptions!$E$15+E9*Assumptions!$E$16 -> 65.319 | F14: =F6*Assumptions!$E$15+F9*Assumptions!$E$16 -> 91.44519 | G14: =G6*Assumptions!$E$15+G9*Assumptions!$E$16 -> 122.55117 | H14: =H6*Assumptions!$E$15+H9*Assumptions!$E$16 -> 160.52408 | I14: =I6*Assumptions!$E$15+I9*Assumptions!$E$16 -> 207.7039 | ... M14: =M6*Assumptions!$E$15+M9*Assumptions!$E$16 -> 562.13608 | N14: =SUM(B14:M14) -> 2342.8297
A15: Hosting + domain + data | B15: =Assumptions!$E$17+Assumptions!$E$18/12+Assumptions!$E$19 -> 11.666667 | C15: =Assumptions!$E$17+Assumptions!$E$18/12+Assumptions!$E$19 -> 11.666667 | D15: =Assumptions!$E$17+Assumptions!$E$18/12+Assumptions!$E$19 -> 11.666667 | E15: =Assumptions!$E$17+Assumptions!$E$18/12+Assumptions!$E$19 -> 11.666667 | F15: =Assumptions!$E$17+Assumptions!$E$18/12+Assumptions!$E$19 -> 11.666667 | G15: =Assumptions!$E$17+Assumptions!$E$18/12+Assumptions!$E$19 -> 11.666667 | H15: =Assumptions!$E$17+Assumptions!$E$18/12+Assumptions!$E$19 -> 11.666667 | I15: =Assumptions!$E$17+Assumptions!$E$18/12+Assumptions!$E$19 -> 11.666667 | ... M15: =Assumptions!$E$17+Assumptions!$E$18/12+Assumptions!$E$19 -> 11.666667 | N15: =SUM(B15:M15) -> 140
A16: Marketing | B16: =Assumptions!$E$20 -> 150 | C16: =Assumptions!$E$20 -> 150 | D16: =Assumptions!$E$20 -> 150 | E16: =Assumptions!$E$20 -> 150 | F16: =Assumptions!$E$20 -> 150 | G16: =Assumptions!$E$20 -> 150 | H16: =Assumptions!$E$20 -> 150 | I16: =Assumptions!$E$20 -> 150 | ... M16: =Assumptions!$E$20 -> 150 | N16: =SUM(B16:M16) -> 1800
A17: TOTAL COSTS | B17: =SUM(B13:B16) -> 176.60667 | C17: =SUM(C13:C16) -> 190.79967 | D17: =SUM(D13:D16) -> 205.85172 | E17: =SUM(E13:E16) -> 233.01013 | F17: =SUM(F13:F16) -> 263.54805 | G17: =SUM(G13:G16) -> 299.11522 | H17: =SUM(H13:H16) -> 341.67505 | I17: =SUM(I13:I16) -> 393.66053 | ... M17: =SUM(M13:M16) -> 772.36263 | N17: =SUM(B17:M17) -> 4515.5463
A18: NET (monthly) | B18: =B12-B17 -> -160.04667 | C18: =C12-C17 -> -158.50767 | D18: =D12-D17 -> -156.87552 | E18: =E12-E17 -> -88.793279 | F18: =F12-F17 -> -22.950083 | G18: =G12-G17 -> 40.937179 | H18: =H12-H17 -> 103.18146 | I18: =I12-I17 -> 164.14262 | ... M18: =M12-M17 -> 405.24139 | N18: =SUM(B18:M18) -> 978.66739
A19: Cumulative net | B19: =B18 -> -160.04667 | C19: =B19+C18 -> -318.55433 | D19: =C19+D18 -> -475.42985 | E19: =D19+E18 -> -564.22313 | F19: =E19+F18 -> -587.17321 | G19: =F19+G18 -> -546.23603 | H19: =G19+H18 -> -443.05457 | I19: =H19+I18 -> -278.91195 | J19: =I19+J18 -> -54.664705 | ... M19: =L19+M18 -> 978.66739 | N19: =M19 -> 978.66739
A20: Blended paid CAC (marketing ÷ new sign-ups) | B20: =IFERROR(B16/B5,0) -> 2.0833333 | C20: =IFERROR(C16/C5,0) -> 1.6025641 | D20: =IFERROR(D16/D5,0) -> 1.2327416 | E20: =IFERROR(E16/E5,0) -> 0.94826278 | F20: =IFERROR(F16/F5,0) -> 0.72943291 | G20: =IFERROR(G16/G5,0) -> 0.56110224 | H20: =IFERROR(H16/H5,0) -> 0.43161711 | I20: =IFERROR(I16/I5,0) -> 0.33201316 | ... M20: =IFERROR(M16/M5,0) -> 0.11624704 | N20: =M20 -> 0.11624704
A22: Total column = 12-month sum for flows; month-12 value for stocks (users, accounts, cumulative net).

Sheet Benchmarks
A1: Competitor & cost benchmarks (verified via web search 2026-10-12; prices change — re-check before quoting)
A3: Name | B3: Segment | C3: Pricing found | D3: Source
A4: Mixel | B4: Home (iOS) | C4: Free; Premium $1.99/mo or $14.99/yr; lifetime $49.99; recipe packs $0.99–$3.99 | D4: https://apps.apple.com/us/app/mixel-cocktail-recipes/id1280464759
A5: Mixel (revenue estimate) | B5: Home | C5: ~$7K est. monthly revenue, <1K monthly downloads (third-party estimate, not official) | D5: https://adapty.io/paywall-library/mixel/
A6: Cocktail Party | B6: Home (iOS) | C6: Reported $4.99 one-time (one review site); another source says $2.99/mo — conflicting | D6: https://appviewable.com/apps/app-cocktail-party-drink-recipes-ingredient-library/
A7: Highball (Studio Neat) | B7: Home recipe cards (iOS) | C7: Free; optional tips $0.99–$9.99; marketing for physical products | D7: https://apps.apple.com/us/app/highball-by-studio-neat/id973319934
A8: Cocktail Flow | B8: Home (iOS) | C8: Premium from $4.99/mo or $24.99/yr | D8: https://apps.apple.com/us/app/cocktail-flow-drink-recipes/id486811622
A9: Home Bar Hero | B9: Home (web/app, AI scan) | C9: Free core; Top Shelf $2.99/mo, $24.99/yr; lifetime listed $49.99 on one page, $99.99 on pricing page | D9: https://homebarhero.ai/pricing/
A10: BottleSnaps | B10: Home (web PWA, AI scan) | C10: Free (3 AI scans/mo, 10 bottles); Home Bar $6/mo | D10: https://bottlesnaps.com/
A11: Elixiary | B11: Home (AI) | C11: Free 3-bottle demo; Curious €3, Apprentice €5.50, Bartender €11, Mixologist €25 per month | D11: https://elixiary.com/pricing
A12: BarShelf | B12: Home (iOS, AI) | C12: Free ≤10 bottles; Pro $3.99/mo or $39.99/yr | D12: https://apps.apple.com/us/app/barshelf-home-bar-ai/id6754469129
A13: Bar Assistant | B13: Home/pro (open source, self-host) | C13: Free self-hosted (MIT) | D13: https://github.com/karlomikus/bar-assistant
A14: Barsys | B14: Hardware + app | C14: Barsys 360 machine $375; app free | D14: https://360.barsys.com/
... A30: Apple Small Business Program | B30: Payments (if native iOS) | C30: 15% commission under $1M proceeds | D30: https://developer.apple.com/app-store/small-business-program/

Sheet Kill-Continue
A1: Decision gates (fill in actuals)
A3: Gate (date) | B3: Metric | C3: Continue if ≥ | D3: Kill / pivot if < | E3: Actual | F3: Decision
A4: Day 30 (2026-11-11) | B4: Strangers who signed up and added ≥5 bottles | C4: 25 | D4: 10
A5: Day 30 | B5: Party menus shared to guests (guest link opened) | C5: 10 | D5: 3
A6: Day 60 (2026-12-11) | B6: Week-4 retention of Day-1–30 cohort | C6: 20% | D6: 10%
A7: Day 60 | B7: Pre-orders / paid Home Pro (any price) | C7: 10 | D7: 3
A8: Day 90 (2027-01-10) | B8: Paying Host/Pro pilots (mobile bartenders / small venues) | C8: 3 | D8: 1
A9: Day 90 | B9: MRR (all sources) | C9: $100 | D9: $25
A10: Ongoing | B10: AI + hosting cost as % of revenue (once revenue > $0) | C10: < 30% | D10: > 60%
